xadix/__init__.py
xadix/dnspod/__init__.py
xadix/dnspod/_objects.py
xadix/dnspod/_version.py
xadix/dnspod/cli.py
xadix_dnspod-0.1.2.dist-info/DESCRIPTION.rst
xadix_dnspod-0.1.2.dist-info/METADATA
xadix_dnspod-0.1.2.dist-info/RECORD
xadix_dnspod-0.1.2.dist-info/WHEEL
xadix_dnspod-0.1.2.dist-info/entry_points.txt
xadix_dnspod-0.1.2.dist-info/metadata.json
xadix_dnspod-0.1.2.dist-info/top_level.txt
